everything/__init__.py
everything/generator.py
everything/utils/magic.py
everything/utils/misc.py
everything/utils/scanner.py
everything-0.1.7.dist-info/licenses/LICENSE.txt
everything-0.1.7.dist-info/METADATA
everything-0.1.7.dist-info/WHEEL
everything-0.1.7.dist-info/top_level.txt
everything-0.1.7.dist-info/RECORD
