Metadata-Version: 2.4
Name: everything
Version: 0.1.7
Summary: from everything import anything
Author-email: Wolf Mermelstein <wolf@404wolf.com>
License: MIT
Requires-Python: >=3.09
License-File: LICENSE.txt
Requires-Dist: typing-extensions>=4.12.2
Requires-Dist: python-dotenv
Requires-Dist: anthropic>=0.75.0
Dynamic: license-file
